emire/__about__.py
emire/__init__.py
emire/letter_cases.py
emire/normalize.py
emi_re-0.1.1.dist-info/METADATA
emi_re-0.1.1.dist-info/WHEEL
emi_re-0.1.1.dist-info/licenses/LICENSE
emi_re-0.1.1.dist-info/RECORD
