Metadata-Version: 2.4
Name: emi-re
Version: 0.1.1
Summary: Collection of regular expressions
Project-URL: Documentation, https://github.com/ftnext/emi-re#readme
Project-URL: Issues, https://github.com/ftnext/emi-re/issues
Project-URL: Source, https://github.com/ftnext/emi-re
Author-email: ftnext <takuyafjp+develop@gmail.com>
License-Expression: MIT
License-File: LICENSE
Keywords: re,regex,regular expression
Classifier: Development Status :: 4 - Beta
Classifier: Intended Audience :: Developers
Classifier: License :: OSI Approved :: MIT License
Classifier: Operating System :: OS Independent
Classifier: Programming Language :: Python
Classifier: Programming Language :: Python :: 3.9
Classifier: Programming Language :: Python :: 3.10
Classifier: Programming Language :: Python :: 3.11
Classifier: Programming Language :: Python :: 3.12
Classifier: Programming Language :: Python :: 3.13
Classifier: Topic :: Software Development :: Libraries :: Python Modules
Classifier: Topic :: Text Processing
Classifier: Topic :: Text Processing :: General
Requires-Python: >=3.9
